nifi_python_swagger_client-1.5.0.dist-info/DESCRIPTION.rst
nifi_python_swagger_client-1.5.0.dist-info/METADATA
nifi_python_swagger_client-1.5.0.dist-info/RECORD
nifi_python_swagger_client-1.5.0.dist-info/WHEEL
nifi_python_swagger_client-1.5.0.dist-info/metadata.json
nifi_python_swagger_client-1.5.0.dist-info/top_level.txt
swagger_client/__init__.py
swagger_client/api_client.py
swagger_client/configuration.py
swagger_client/rest.py
swagger_client/apis/__init__.py
swagger_client/apis/access_api.py
swagger_client/apis/connections_api.py
swagger_client/apis/controller_api.py
swagger_client/apis/controllerservices_api.py
swagger_client/apis/counters_api.py
swagger_client/apis/datatransfer_api.py
swagger_client/apis/flow_api.py
swagger_client/apis/flowfilequeues_api.py
swagger_client/apis/funnel_api.py
swagger_client/apis/inputports_api.py
swagger_client/apis/labels_api.py
swagger_client/apis/outputports_api.py
swagger_client/apis/policies_api.py
swagger_client/apis/processgroups_api.py
swagger_client/apis/processors_api.py
swagger_client/apis/provenance_api.py
swagger_client/apis/provenanceevents_api.py
swagger_client/apis/remoteprocessgroups_api.py
swagger_client/apis/reportingtasks_api.py
swagger_client/apis/resources_api.py
swagger_client/apis/sitetosite_api.py
swagger_client/apis/snippets_api.py
swagger_client/apis/systemdiagnostics_api.py
swagger_client/apis/templates_api.py
swagger_client/apis/tenants_api.py
swagger_client/apis/versions_api.py
swagger_client/models/__init__.py
swagger_client/models/about_dto.py
swagger_client/models/about_entity.py
swagger_client/models/access_configuration_dto.py
swagger_client/models/access_configuration_entity.py
swagger_client/models/access_policy_dto.py
swagger_client/models/access_policy_entity.py
swagger_client/models/access_policy_summary_dto.py
swagger_client/models/access_policy_summary_entity.py
swagger_client/models/access_status_dto.py
swagger_client/models/access_status_entity.py
swagger_client/models/action_details_dto.py
swagger_client/models/action_dto.py
swagger_client/models/action_entity.py
swagger_client/models/activate_controller_services_entity.py
swagger_client/models/affected_component_dto.py
swagger_client/models/affected_component_entity.py
